README.md
setup.cfg
setup.py
pyinfer/__init__.py
pyinfer/errors.py
pyinfer/inference_report.py
pyinfer.egg-info/PKG-INFO
pyinfer.egg-info/SOURCES.txt
pyinfer.egg-info/dependency_links.txt
pyinfer.egg-info/requires.txt
pyinfer.egg-info/top_level.txt
test/test_inference_report.py
test/test_multi_inference_report.py