Metadata-Version: 2.1
Name: pyinfer
Version: 0.0.2
Summary: Pyinfer is a model agnostic Python utility tool for ML developers and researchers to benchmark model inference statistics.
Home-page: https://github.com/cdpierse/pyinfer
Author: Charles Pierse
Author-email: charlespierse@gmail.com
License: Apache-2.0
Keywords: machine learning,inference,benchmark,model inference,model serving
Platform: UNKNOWN
Classifier: Development Status :: 3 - Alpha
Classifier: Intended Audience :: Developers
Classifier: Topic :: Software Development :: Libraries :: Python Modules
Classifier: Programming Language :: Python :: 3.8
Provides-Extra: Plotting
Provides-Extra: all
